Recipyzer/__init__.py
Recipyzer/compile_metadata.py
recipyzer-0.1.0a4.dist-info/LICENSE.md
recipyzer-0.1.0a4.dist-info/METADATA
recipyzer-0.1.0a4.dist-info/WHEEL
recipyzer-0.1.0a4.dist-info/entry_points.txt
recipyzer-0.1.0a4.dist-info/top_level.txt
recipyzer-0.1.0a4.dist-info/RECORD
