Metadata-Version: 2.1
Name: recipyzer
Version: 0.1.0a4
Summary: A toolkit for managing and organizing the Recipyzer recipe repository.
Home-page: https://github.com/kmcconnell/recipyzer
Author: Kane McConnell
License: UNKNOWN
Platform: UNKNOWN
Classifier: Programming Language :: Python :: 3
Classifier: License :: OSI Approved :: MIT License
Classifier: Operating System :: OS Independent
Requires-Python: >=3.6
Requires-Dist: frontmatter
